README
assert_select.py
setup.py
assert_select.egg-info/PKG-INFO
assert_select.egg-info/SOURCES.txt
assert_select.egg-info/dependency_links.txt
assert_select.egg-info/not-zip-safe
assert_select.egg-info/requires.txt
assert_select.egg-info/top_level.txt
test/test_assert_select.py