Metadata-Version: 1.0
Name: assert-select
Version: 1.0.1
Summary: Make assertions about CSS selectors
Home-page: http://github.com/aroberts/assert-select
Author: Andrew Roberts
Author-email: adroberts@gmail.com
License: BSD
Platform: any
